{
	"name": "PL_abs_to_adlsgen2",
	"properties": {
		"activities": [
			{
				"name": "get_metadata_childitems1",
				"type": "GetMetadata",
				"dependsOn": [],
				"policy": {
					"timeout": "0.12:00:00",
					"retry": 0,
					"retryIntervalInSeconds": 30,
					"secureOutput": true,
					"secureInput": false
				},
				"userProperties": [],
				"typeProperties": {
					"dataset": {
						"referenceName": "DS_ABS_source1",
						"type": "DatasetReference"
					},
					"fieldList": [
						"childItems"
					],
					"storeSettings": {
						"type": "AzureBlobStorageReadSettings",
						"recursive": true,
						"enablePartitionDiscovery": false
					},
					"formatSettings": {
						"type": "DelimitedTextReadSettings"
					}
				}
			},
			{
				"name": "ForEach1",
				"type": "ForEach",
				"dependsOn": [
					{
						"activity": "get_metadata_childitems1",
						"dependencyConditions": [
							"Succeeded"
						]
					}
				],
				"userProperties": [],
				"typeProperties": {
					"items": {
						"value": "@activity('get_metadata_childitems1').output.childItems",
						"type": "Expression"
					},
					"isSequential": true,
					"activities": [
						{
							"name": "Copy data1",
							"type": "Copy",
							"dependsOn": [],
							"policy": {
								"timeout": "0.12:00:00",
								"retry": 0,
								"retryIntervalInSeconds": 30,
								"secureOutput": true,
								"secureInput": false
							},
							"userProperties": [],
							"typeProperties": {
								"source": {
									"type": "DelimitedTextSource",
									"storeSettings": {
										"type": "AzureBlobStorageReadSettings",
										"recursive": true,
										"wildcardFileName": "*.CSV",
										"enablePartitionDiscovery": false
									},
									"formatSettings": {
										"type": "DelimitedTextReadSettings"
									}
								},
								"sink": {
									"type": "DelimitedTextSink",
									"storeSettings": {
										"type": "AzureBlobFSWriteSettings"
									},
									"formatSettings": {
										"type": "DelimitedTextWriteSettings",
										"quoteAllText": true,
										"fileExtension": ".CSV"
									}
								},
								"enableStaging": false,
								"translator": {
									"type": "TabularTranslator",
									"typeConversion": true,
									"typeConversionSettings": {
										"allowDataTruncation": true,
										"treatBooleanAsNumber": false
									}
								}
							},
							"inputs": [
								{
									"referenceName": "DS_ABS_csv1",
									"type": "DatasetReference"
								}
							],
							"outputs": [
								{
									"referenceName": "DS_ADSL_Gen2_Sink",
									"type": "DatasetReference"
								}
							]
						}
					]
				}
			}
		],
		"folder": {
			"name": "kpl"
		},
		"annotations": [],
		"lastPublishTime": "2023-03-13T08:33:15Z"
	},
	"type": "Microsoft.DataFactory/factories/pipelines"
}